Metadata-Version: 2.1
Name: pystatsd-tags
Version: 0.0.4
Summary: Datadog tags implementation for statsd.
Home-page: UNKNOWN
Author: Sam Pegler
Author-email: sam@sampegler.co.uk
License: MIT
Platform: UNKNOWN
Requires-Python: >3.6.0
Provides-Extra: docs
Provides-Extra: test
